setup.py
WebToolbox.egg-info/PKG-INFO
WebToolbox.egg-info/SOURCES.txt
WebToolbox.egg-info/dependency_links.txt
WebToolbox.egg-info/not-zip-safe
WebToolbox.egg-info/top_level.txt
bin/check_site.py
bin/http_bench.py
bin/log_replay.py
bin/red_spider.py
bin/wk_bench.py
webtoolbox/__init__.py
webtoolbox/clients.py