Metadata-Version: 1.1
Name: WebToolbox
Version: 0.2
Summary: Framework and tools for working with web servers
Home-page: http://acdha.github.com/webtoolbox/
Author: Chris Adams
Author-email: chris@improbable.org
License: BSD License
Platform: OS Independent
Classifier: Development Status :: 4 - Beta
Classifier: Environment :: Web Environment
Classifier: Intended Audience :: Developers
Classifier: License :: OSI Approved :: BSD License
Classifier: Operating System :: OS Independent
Classifier: Programming Language :: Python
Classifier: Topic :: Internet :: WWW/HTTP :: Dynamic Content
Classifier: Topic :: Software Development
Classifier: Topic :: Software Development :: Libraries :: Application Frameworks
Requires: lxml
Requires: pycurl (>=7.16.4)
Requires: tornado
Requires: html5lib
Requires: chardet
